langchain_amazon_nova/__init__.py
langchain_amazon_nova/_exceptions.py
langchain_amazon_nova/chat_models.py
langchain_amazon_nova/py.typed
langchain_amazon_nova/data/__init__.py
langchain_amazon_nova/data/_profiles.py
langchain_amazon_nova/data/profile_augmentations.toml
langchain_amazon_nova-1.0.1.dist-info/METADATA
langchain_amazon_nova-1.0.1.dist-info/WHEEL
langchain_amazon_nova-1.0.1.dist-info/licenses/LICENSE.txt
langchain_amazon_nova-1.0.1.dist-info/RECORD
