Metadata-Version: 2.4
Name: langchain-amazon-nova
Version: 1.0.1
Summary: An integration package connecting Amazon Nova and LangChain
Project-URL: Source Code, https://github.com/amazon-nova-api/langchain-amazon-nova/tree/main/libs/amazon_nova
Project-URL: repository, https://github.com/amazon-nova-api/langchain-amazon-nova
License: MIT
License-File: LICENSE.txt
Keywords: ai,amazon,langchain,llm,nova
Classifier: Development Status :: 4 - Beta
Classifier: Intended Audience :: Developers
Classifier: License :: OSI Approved :: MIT License
Classifier: Programming Language :: Python :: 3
Classifier: Programming Language :: Python :: 3.10
Classifier: Programming Language :: Python :: 3.11
Classifier: Programming Language :: Python :: 3.12
Classifier: Programming Language :: Python :: 3.13
Classifier: Topic :: Scientific/Engineering :: Artificial Intelligence
Classifier: Topic :: Software Development :: Libraries :: Python Modules
Requires-Python: >=3.10
Requires-Dist: httpx>=0.27.0
Requires-Dist: langchain-core<2.0.0,>=1.1.0
Requires-Dist: openai<3.0.0,>=1.109.1
Requires-Dist: typing-extensions>=4.0.0
